exoyone/__init__.py
exoyone/__main__.py
exoyone/cli/__init__.py
exoyone/cli/cli.py
exoyone/cli/get.py
exoyone/cli/helpers.py
exoyone/cli/set.py
exoyone/exoyone.py
exoyone/models.py
exoyone/py.typed
exoyone/state.py
moxyone/__init__.py
moxyone/__main__.py
moxyone/moxyone.py
pyexoyone-1.0.11.dist-info/METADATA
pyexoyone-1.0.11.dist-info/WHEEL
pyexoyone-1.0.11.dist-info/entry_points.txt
pyexoyone-1.0.11.dist-info/licenses/LICENSE
pyexoyone-1.0.11.dist-info/RECORD
