Metadata-Version: 2.4
Name: pyExoyOne
Version: 1.0.11
Summary: Python library to configure and control the Exoy(tm) ONE.
License: MIT
License-File: LICENSE
Keywords: exoy,exoyone,infinite-dodecahedron
Author: Avi Miller
Author-email: me@dje.li
Requires-Python: >=3.12,<4.0
Classifier: Development Status :: 4 - Beta
Classifier: Environment :: Console
Classifier: Framework :: AsyncIO
Classifier: Framework :: MkDocs
Classifier: Framework :: Pytest
Classifier: Intended Audience :: Developers
Classifier: License :: OSI Approved :: MIT License
Classifier: Natural Language :: English
Classifier: Operating System :: OS Independent
Classifier: Programming Language :: Python :: 3
Classifier: Programming Language :: Python :: 3.12
Classifier: Programming Language :: Python :: 3.13
Classifier: Programming Language :: Python :: 3.14
Classifier: Topic :: Home Automation
Classifier: Topic :: Software Development :: Libraries
Classifier: Topic :: Software Development :: Libraries :: Python Modules
Classifier: Topic :: Utilities
Classifier: Typing :: Typed
Requires-Dist: asyncio-dgram (>=2.2.0,<3.0.0)
Requires-Dist: backoff (>=2.2.1,<3.0.0)
Requires-Dist: camel-converter (>=5.0.0,<6.0.0)
Requires-Dist: rich (>=10)
Requires-Dist: typer (>=0.20.0,<0.21.0)
Requires-Dist: zeroconf (>=0.148.0,<0.149.0)
Project-URL: Changelog, https://github.com/Djelibeybi/pyExoyOne/blob/main/CHANGELOG.md
Project-URL: Documentation, https://djelibeybi.github.io/pyExoyOne/
Project-URL: Homepage, https://djelibeybi.github.io/pyExoyOne/
Project-URL: Issues, https://github.com/Djelibeybi/pyExoyOne/issues
Project-URL: Repository, https://github.com/Djelibeybi/pyExoyOne/
